commoncontent/__init__.py
commoncontent/admin.py
commoncontent/apps.py
commoncontent/common.py
commoncontent/models.py
commoncontent/redirects.py
commoncontent/schemas.py
commoncontent/sitemaps.py
commoncontent/urls.py
commoncontent/views.py
commoncontent/views_optional.py
commoncontent/management/__init__.py
commoncontent/management/commands/__init__.py
commoncontent/management/commands/import_markdown.py
commoncontent/migrations/0001_initial.py
commoncontent/migrations/0002_article_subtitle_attachment_custom_icon_and_more.py
commoncontent/migrations/0003_add_image_set_attachment_set.py
commoncontent/migrations/__init__.py
commoncontent/static/generic.css
commoncontent/templates/commoncontent/article_detail.html
commoncontent/templates/commoncontent/base.html
commoncontent/templates/commoncontent/blocks/article_list_album.html
commoncontent/templates/commoncontent/blocks/article_list_blog.html
commoncontent/templates/commoncontent/blocks/article_text.html
commoncontent/templates/commoncontent/blocks/author_list_album.html
commoncontent/templates/commoncontent/blocks/author_profile.html
commoncontent/templates/commoncontent/blocks/debug_newsite.html
commoncontent/templates/commoncontent/blocks/empty.html
commoncontent/templates/commoncontent/blocks/footer_simple.html
commoncontent/templates/commoncontent/blocks/header_simple.html
commoncontent/templates/commoncontent/includes/article_series.html
commoncontent/templates/commoncontent/includes/link_list.html
commoncontent/templates/commoncontent/includes/messages.html
commoncontent/templates/commoncontent/includes/pagination.html
commoncontent/templates/registration/logged_out.html
commoncontent/templates/registration/login.html
commoncontent/templates/registration/password_change_done.html
commoncontent/templates/registration/password_change_form.html
commoncontent/templates/registration/password_reset_complete.html
commoncontent/templates/registration/password_reset_confirm.html
django_commoncontent-0.4.0.dist-info/licenses/LICENSE
django_commoncontent-0.4.0.dist-info/METADATA
django_commoncontent-0.4.0.dist-info/WHEEL
django_commoncontent-0.4.0.dist-info/top_level.txt
django_commoncontent-0.4.0.dist-info/RECORD
