Metadata-Version: 2.4
Name: django-commoncontent
Version: 0.4.0
Summary: basic data model and templates for Django's generic views to produce a decent-looking website with minimal effort
Author-email: Vince Veselosky <vince@control-escape.com>
Project-URL: Homepage, https://github.com/veselosky/django-commoncontent
Project-URL: Bug Tracker, https://github.com/veselosky/django-commoncontent/issues
Classifier: Programming Language :: Python :: 3
Classifier: License :: OSI Approved :: Apache Software License
Classifier: Operating System :: OS Independent
Requires-Python: >=3.8
License-File: LICENSE
Requires-Dist: django-bootstrap-icons>=0.7.8
Requires-Dist: django-imagekit>=5.0.0
Requires-Dist: django-sitevars>=2.0.0
Requires-Dist: django-taggit>=5.0.0
Requires-Dist: django>=4.2
Requires-Dist: pillow>=10.1.0
Requires-Dist: pygments>=2.18.0
Requires-Dist: python-dateutil>=2.8.1
Requires-Dist: pyyaml>=6.0.1
Requires-Dist: mistletoe>=1.3.0
Provides-Extra: dev
Requires-Dist: django-debug-toolbar>=4.4.6; extra == "dev"
Requires-Dist: django-environ>=0.11.2; extra == "dev"
Requires-Dist: django-extensions>=3.2.3; extra == "dev"
Requires-Dist: django-tinymce>=4.1.0; extra == "dev"
Requires-Dist: djlint>=1.35.2; extra == "dev"
Requires-Dist: docutils>=0.20.1; extra == "dev"
Requires-Dist: pre-commit>=3.5.0; extra == "dev"
Requires-Dist: pytest>=8.3.2; extra == "dev"
Requires-Dist: pytest-cov>=5.0.0; extra == "dev"
Requires-Dist: pytest-django>=4.8.0; extra == "dev"
Dynamic: license-file
